easyproc.py
easyproc-0.6.0.dist-info/LICENSE
easyproc-0.6.0.dist-info/METADATA
easyproc-0.6.0.dist-info/WHEEL
easyproc-0.6.0.dist-info/top_level.txt
easyproc-0.6.0.dist-info/RECORD
