Metadata-Version: 2.1
Name: easyproc
Version: 0.6.0
Summary: thin abstraction on subprocess.run to simplify admin scripts
Home-page: https://github.com/ninjaaron/easyproc
Author: Aaron Christianson
Author-email: ninjaaron@gmail.com
License: MPL-2.0
Keywords: shell pipe subprcess process scripting
Platform: UNKNOWN
Classifier: Programming Language :: Python :: 3.5
